{
  "type": "minecraft:entity",
  "pools": [
    {
      "rolls": 10,
      "entries": [
        {
          "type": "minecraft:item",
          "weight": 70,
          "name": "minecraft:emerald",
          "functions": [
            {
              "function": "minecraft:set_count",
              "count": {
                "min": 1,
                "max": 5
              }
            }
          ]
        },
        {
          "type": "minecraft:item",
          "weight": 100,
          "name": "minecraft:rotten_flesh",
          "functions": [
            {
              "function": "minecraft:set_count",
              "count": {
                "min": 32,
                "max": 64
              }
            }
          ]
        },
        {
          "type": "minecraft:item",
          "weight": 25,
          "name": "minecraft:deepslate_diamond_ore",
          "functions": [
            {
              "function": "minecraft:set_count",
              "count": {
                "min": 1,
                "max": 4
              }
            }
          ]
        },
        {
          "type": "minecraft:item",
          "weight": 25,
          "name": "minecraft:gold_ingot",
          "functions": [
            {
              "function": "minecraft:set_count",
              "count": {
                "min": 1,
                "max": 4
              }
            }
          ]
        },
        {
          "type": "minecraft:item",
          "weight": 25,
          "name": "minecraft:lapis_lazuli",
          "functions": [
            {
              "function": "minecraft:set_count",
              "count": {
                "min": 1,
                "max": 4
              }
            }
          ]
        },
        {
          "type": "minecraft:item",
          "weight": 25,
          "name": "minecraft:redstone_block",
          "functions": [
            {
              "function": "minecraft:set_count",
              "count": {
                "min": 1,
                "max": 4
              }
            }
          ]
        },
        {
          "type": "minecraft:item",
          "weight": 10,
          "name": "minecraft:netherite_scrap",
          "functions": [
            {
              "function": "minecraft:set_count",
              "count": {
                "min": 1,
                "max": 2
              }
            }
          ]
        },
        {
          "type": "minecraft:item",
          "weight": 150,
          "name": "minecraft:soul_soil",
          "functions": [
            {
              "function": "minecraft:set_count",
              "count": {
                "min": 1,
                "max": 3
              }
            }
          ]
        },
        {
          "type": "minecraft:item",
          "weight":200,
          "functions": [
            {
              "function": "minecraft:set_count",
              "count": {
                "min": 48,
                "max": 64
              }
            },
            {
              "function": "minecraft:set_nbt",
              "tag": "{CustomModelData:1,display:{Name:'[{\"text\":\"ruby\"}]'}}"
            }
          ],
          "name": "minecraft:slime_ball"
        },
        {
          "type": "minecraft:item",
          "weight": 400,
          "name": "minecraft:nautilus_shell",
          "functions": [
            {
              "function": "minecraft:set_count",
              "count": {
                "min": 1,
                "max": 12
              }
            },
            {
              "function": "minecraft:set_nbt",
              "tag": "{CustomModelData:37,display:{Name:'[{\"text\":\"note\"}]'}}"
            }
          ]
        },
        {
          "type": "minecraft:item",
          "weight": 20,
          "name": "minecraft:netherite_sword",
          "functions": [
            {
              "function": "minecraft:set_count",
              "count": {
                "min": 1,
                "max": 1
              }
            },
            {
              "function": "minecraft:set_nbt",
              "tag": "{CustomModelData:15,Enchantments:[{id:\"minecraft:sharpness\",lvl:6s}],display:{Name:'[{\"text\":\"tuba\"}]'}}"
            }
          ]
        },
        {
          "type": "minecraft:item",
          "weight": 20,
          "name": "minecraft:netherite_sword",
          "functions": [
            {
              "function": "minecraft:set_count",
              "count": {
                "min": 1,
                "max": 1
              }
            },
            {
              "function": "minecraft:set_nbt",
              "tag": "{CustomModelData:16,Enchantments:[{id:\"minecraft:smite\",lvl:6s}],display:{Name:'[{\"text\":\"horn\"}]'}}"
            }
          ]
        }
      ]
    }
  ]
}